wagtailmenus/__init__.py
wagtailmenus/apps.py
wagtailmenus/context_processors.py
wagtailmenus/errors.py
wagtailmenus/forms.py
wagtailmenus/managers.py
wagtailmenus/menuadmin.py
wagtailmenus/panels.py
wagtailmenus/wagtail_hooks.py
wagtailmenus/conf/__init__.py
wagtailmenus/conf/constants.py
wagtailmenus/conf/defaults.py
wagtailmenus/conf/settings.py
wagtailmenus/conf/tests/__init__.py
wagtailmenus/conf/tests/test_menuadmin_disable_settings.py
wagtailmenus/development/__init__.py
wagtailmenus/locale/ar/LC_MESSAGES/django.mo
wagtailmenus/locale/ar/LC_MESSAGES/django.po
wagtailmenus/locale/de/LC_MESSAGES/django.mo
wagtailmenus/locale/de/LC_MESSAGES/django.po
wagtailmenus/locale/en/LC_MESSAGES/django.mo
wagtailmenus/locale/en/LC_MESSAGES/django.po
wagtailmenus/locale/es_419/LC_MESSAGES/django.mo
wagtailmenus/locale/es_419/LC_MESSAGES/django.po
wagtailmenus/locale/fr/LC_MESSAGES/django.mo
wagtailmenus/locale/fr/LC_MESSAGES/django.po
wagtailmenus/locale/id/LC_MESSAGES/django.mo
wagtailmenus/locale/id/LC_MESSAGES/django.po
wagtailmenus/locale/it/LC_MESSAGES/django.mo
wagtailmenus/locale/it/LC_MESSAGES/django.po
wagtailmenus/locale/lt/LC_MESSAGES/django.mo
wagtailmenus/locale/lt/LC_MESSAGES/django.po
wagtailmenus/locale/nl/LC_MESSAGES/django.mo
wagtailmenus/locale/nl/LC_MESSAGES/django.po
wagtailmenus/locale/pt_BR/LC_MESSAGES/django.mo
wagtailmenus/locale/pt_BR/LC_MESSAGES/django.po
wagtailmenus/locale/ru/LC_MESSAGES/django.mo
wagtailmenus/locale/ru/LC_MESSAGES/django.po
wagtailmenus/locale/uk/LC_MESSAGES/django.mo
wagtailmenus/locale/uk/LC_MESSAGES/django.po
wagtailmenus/locale/zh_CN/LC_MESSAGES/django.mo
wagtailmenus/locale/zh_CN/LC_MESSAGES/django.po
wagtailmenus/management/__init__.py
wagtailmenus/management/commands/__init__.py
wagtailmenus/management/commands/autopopulate_main_menus.py
wagtailmenus/migrations/0001_initial.py
wagtailmenus/migrations/0002_auto_20160129_0901.py
wagtailmenus/migrations/0003_auto_20160129_2339.py
wagtailmenus-4.0.4.dist-info/licenses/LICENSE.txt
wagtailmenus-4.0.4.dist-info/METADATA
wagtailmenus-4.0.4.dist-info/WHEEL
wagtailmenus-4.0.4.dist-info/top_level.txt
wagtailmenus-4.0.4.dist-info/RECORD
