Metadata-Version: 2.4
Name: wagtailmenus
Version: 4.0.4
Summary: An app to help you manage menus in your Wagtail projects more consistently.
Home-page: https://github.com/jazzband/wagtailmenus
Author: Andy Babic
Author-email: ababic@rkh.co.uk
License: MIT
Keywords: wagtail cms model utility
Classifier: Environment :: Web Environment
Classifier: Intended Audience :: Developers
Classifier: Operating System :: OS Independent
Classifier: Programming Language :: Python
Classifier: Programming Language :: Python :: 3
Classifier: Programming Language :: Python :: 3.9
Classifier: Programming Language :: Python :: 3.10
Classifier: Programming Language :: Python :: 3.11
Classifier: Programming Language :: Python :: 3.12
Classifier: Programming Language :: Python :: 3.13
Classifier: Framework :: Django
Classifier: Framework :: Django :: 4.2
Classifier: Framework :: Django :: 5.1
Classifier: Framework :: Django :: 5.2
Classifier: Framework :: Wagtail :: 6
Classifier: Framework :: Wagtail :: 7
Classifier: Topic :: Internet :: WWW/HTTP
Classifier: Topic :: Internet :: WWW/HTTP :: Dynamic Content
Requires-Python: >=3.9
License-File: LICENSE.txt
Requires-Dist: wagtail>=6.3
Requires-Dist: django-cogwheels==0.3
Provides-Extra: testing
Requires-Dist: beautifulsoup4<4.10,>=4.8; extra == "testing"
Requires-Dist: coverage>=4.5; extra == "testing"
Requires-Dist: django-webtest<1.10,>=1.9; extra == "testing"
Provides-Extra: docs
Requires-Dist: pyenchant>=2.0; extra == "docs"
Requires-Dist: Sphinx>=1.7.4; extra == "docs"
Requires-Dist: sphinxcontrib-spelling>=1.4; extra == "docs"
Requires-Dist: sphinx_rtd_theme>=0.3; extra == "docs"
Provides-Extra: development
Requires-Dist: wagtail>=6.3; extra == "development"
Requires-Dist: django-debug-toolbar; extra == "development"
Requires-Dist: django-extensions; extra == "development"
Requires-Dist: ipdb; extra == "development"
Requires-Dist: werkzeug; extra == "development"
Requires-Dist: beautifulsoup4<4.10,>=4.8; extra == "development"
Requires-Dist: coverage>=4.5; extra == "development"
Requires-Dist: django-webtest<1.10,>=1.9; extra == "development"
Provides-Extra: deployment
Dynamic: author
Dynamic: author-email
Dynamic: classifier
Dynamic: description
Dynamic: home-page
Dynamic: keywords
Dynamic: license
Dynamic: license-file
Dynamic: provides-extra
Dynamic: requires-dist
Dynamic: requires-python
Dynamic: summary
